perception_model-1.0.dist-info/METADATA
perception_model-1.0.dist-info/RECORD
perception_model-1.0.dist-info/WHEEL
perception_model-1.0.dist-info/entry_points.txt
perception_model-1.0.dist-info/top_level.txt
perceptual_model/__init__.py
perceptual_model/perceptual_model.py
scripts/__init__.py
scripts/filter_screenshot.py
scripts/filter_screenshot_gui.py
scripts/util.py
