Metadata-Version: 2.1
Name: perception-model
Version: 1.0
Summary: Perception Model
Home-page: https://github.com/fkerber/perception-model-tool
Author: Michael Mauderer, Frederic Kerber
Author-email: fkerber@gmail.com
License: GNU Lesser General Public License v3.0
Platform: UNKNOWN
Requires-Python: >=3
Requires-Dist: numpy
Requires-Dist: scipy
Requires-Dist: colour-science
Requires-Dist: click
